swolfpy/LCA_matrix.py
swolfpy/Monte_Carlo.py
swolfpy/Optimization.py
swolfpy/Parameters.py
swolfpy/ProcessDB.py
swolfpy/Project.py
swolfpy/Required_keys.py
swolfpy/Technosphere.py
swolfpy/__init__.py
swolfpy/__main__.py
swolfpy/swolfpy_method.py
swolfpy/utils.py
swolfpy/UI/MC_ui.py
swolfpy/UI/PySWOLF_run.py
swolfpy/UI/PySWOLF_ui.py
swolfpy/UI/PyWOLF_Resource_rc.py
swolfpy/UI/Reference_ui.py
swolfpy/UI/Table_from_pandas.py
swolfpy/UI/Workers.py
swolfpy/UI/__init__.py
swolfpy/UI/adv_opt_ui.py
swolfpy-1.4.0.dist-info/AUTHORS.rst
swolfpy-1.4.0.dist-info/LICENSE.md
swolfpy-1.4.0.dist-info/METADATA
swolfpy-1.4.0.dist-info/WHEEL
swolfpy-1.4.0.dist-info/entry_points.txt
swolfpy-1.4.0.dist-info/top_level.txt
swolfpy-1.4.0.dist-info/RECORD
