Metadata-Version: 2.1
Name: swolfpy
Version: 1.4.0
Summary: Solid Waste Optimization Life-cycle Framework in Python(SwolfPy).
Author-email: Mojtaba Sardarmehni <msardar2@alumni.ncsu.edu>
Maintainer-email: Mojtaba Sardarmehni <msardar2@alumni.ncsu.edu>
License: GNU GENERAL PUBLIC LICENSE V2
Project-URL: Homepage, https://swolfpy-project.github.io/
Project-URL: Documentation, https://swolfpy.readthedocs.io/en/latest/
Project-URL: Source Code, https://github.com/SwolfPy-Project/swolfpy
Keywords: LCA,solid_waste,waste_management,swolfpy,brightway2
Classifier: Development Status :: 5 - Production/Stable
Classifier: Intended Audience :: Education
Classifier: Intended Audience :: Science/Research
Classifier: License :: OSI Approved :: GNU General Public License v2 (GPLv2)
Classifier: Natural Language :: English
Classifier: Programming Language :: Python :: 3.9
Classifier: Operating System :: MacOS :: MacOS X
Classifier: Operating System :: Microsoft :: Windows
Classifier: Topic :: Scientific/Engineering :: Information Analysis
Classifier: Topic :: Scientific/Engineering :: Mathematics
Classifier: Topic :: Scientific/Engineering :: Visualization
Classifier: Natural Language :: English
Requires-Python: >=3.9
License-File: LICENSE.md
License-File: AUTHORS.rst
Requires-Dist: brightway2 ==2.4.1
Requires-Dist: bw-migrations ==0.1
Requires-Dist: bw2analyzer ==0.10
Requires-Dist: bw2calc ==1.8.2
Requires-Dist: bw2data ==3.6.6
Requires-Dist: bw2io ==0.8.7
Requires-Dist: bw2parameters ==1.1.0
Requires-Dist: coverage
Requires-Dist: graphviz
Requires-Dist: jupyter
Requires-Dist: pandas ==2.0.*
Requires-Dist: numpy ==1.24.*
Requires-Dist: plotly
Requires-Dist: pyDOE
Requires-Dist: PySide2 ==5.15.2.1
Requires-Dist: pytest
Requires-Dist: pytest-cov
Requires-Dist: pytest-flake8
Requires-Dist: scipy ==1.8.0
Requires-Dist: swolfpy-inputdata ==1.1.*
Requires-Dist: swolfpy-processmodels ==1.1.*
Requires-Dist: xlrd ==1.2.0
